freddie/__init__.py
freddie/exceptions.py
freddie/helpers.py
freddie/schemas.py
freddie/db/__init__.py
freddie/db/depends_decorator.py
freddie/db/fields.py
freddie/db/models.py
freddie/db/queries.py
freddie/viewsets/__init__.py
freddie/viewsets/dependencies.py
freddie/viewsets/generics.py
freddie/viewsets/mixins.py
freddie/viewsets/route_decorator.py
freddie/viewsets/signals.py
freddie/viewsets/sql.py
Freddie-0.9.8.dist-info/LICENSE
Freddie-0.9.8.dist-info/WHEEL
Freddie-0.9.8.dist-info/METADATA
Freddie-0.9.8.dist-info/RECORD
