Metadata-Version: 2.1
Name: Freddie
Version: 0.9.8
Summary: FastAPI tools library for building DRF-like viewsets
Author-email: Arseny Gabdullin <a.gabdullin@tinkoff.ru>
Requires-Python: >=3.6
Classifier: Intended Audience :: Information Technology
Classifier: Intended Audience :: System Administrators
Classifier: Intended Audience :: Developers
Classifier: Operating System :: OS Independent
Classifier: Programming Language :: Python
Classifier: Programming Language :: Python :: 3
Classifier: Programming Language :: Python :: 3 :: Only
Classifier: Programming Language :: Python :: 3.6
Classifier: Programming Language :: Python :: 3.7
Classifier: Typing :: Typed
Classifier: Environment :: Web Environment
Classifier: Framework :: AsyncIO
Classifier: Topic :: Software Development :: Libraries :: Application Frameworks
Classifier: Topic :: Software Development :: Libraries :: Python Modules
Classifier: Topic :: Software Development :: Libraries
Classifier: Topic :: Software Development
Classifier: Topic :: Internet :: WWW/HTTP :: HTTP Servers
Classifier: Topic :: Internet :: WWW/HTTP
Classifier: Topic :: Internet
Classifier: License :: OSI Approved :: MIT License
Requires-Dist: fastapi >=0.62
Requires-Dist: aiopg >= 1.0.0 ; extra == "db"
Requires-Dist: peewee-async == 0.7.0 ; extra == "db"
Requires-Dist: peewee == 3.13.3 ; extra == "db"
Requires-Dist: uvicorn ; extra == "dev"
Requires-Dist: pytest >=4.0.0 ; extra == "test"
Requires-Dist: pytest-asyncio ; extra == "test"
Requires-Dist: pytest-cov ; extra == "test"
Requires-Dist: pytest-randomly ; extra == "test"
Requires-Dist: python-dotenv ; extra == "test"
Requires-Dist: factory-boy ; extra == "test"
Requires-Dist: async-asgi-testclient ; extra == "test"
Requires-Dist: mypy ; extra == "test"
Requires-Dist: black ; extra == "test"
Requires-Dist: isort ; extra == "test"
Requires-Dist: flake8 ; extra == "test"
Project-URL: Source, https://github.com/tinkoffjournal/freddie
Provides-Extra: db
Provides-Extra: dev
Provides-Extra: test
